Qt5BianchengRumenjiaochengCYuyanZhongwenwang/README.md
Qt5BianchengRumenjiaochengCYuyanZhongwenwang/__init__.py
Qt5BianchengRumenjiaochengCYuyanZhongwenwang/__main__.py
Qt5BianchengRumenjiaochengCYuyanZhongwenwang/file.epub
Qt5BianchengRumenjiaochengCYuyanZhongwenwang/index.html
Qt5BianchengRumenjiaochengCYuyanZhongwenwang/css/__init__.py
Qt5BianchengRumenjiaochengCYuyanZhongwenwang/css/annotations.css
Qt5BianchengRumenjiaochengCYuyanZhongwenwang/css/main.css
Qt5BianchengRumenjiaochengCYuyanZhongwenwang/css/normalize.css
Qt5BianchengRumenjiaochengCYuyanZhongwenwang/css/popup.css
Qt5BianchengRumenjiaochengCYuyanZhongwenwang/font/__init__.py
Qt5BianchengRumenjiaochengCYuyanZhongwenwang/font/fontello.eot
Qt5BianchengRumenjiaochengCYuyanZhongwenwang/font/fontello.svg
Qt5BianchengRumenjiaochengCYuyanZhongwenwang/font/fontello.ttf
Qt5BianchengRumenjiaochengCYuyanZhongwenwang/font/fontello.woff
Qt5BianchengRumenjiaochengCYuyanZhongwenwang/img/__init__.py
Qt5BianchengRumenjiaochengCYuyanZhongwenwang/img/annotator-glyph-sprite.png
Qt5BianchengRumenjiaochengCYuyanZhongwenwang/img/annotator-icon-sprite.png
Qt5BianchengRumenjiaochengCYuyanZhongwenwang/img/apple-touch-icon.png
Qt5BianchengRumenjiaochengCYuyanZhongwenwang/img/cancelfullscreen.png
Qt5BianchengRumenjiaochengCYuyanZhongwenwang/img/close.png
Qt5BianchengRumenjiaochengCYuyanZhongwenwang/img/fullscreen.png
Qt5BianchengRumenjiaochengCYuyanZhongwenwang/img/loader.gif
Qt5BianchengRumenjiaochengCYuyanZhongwenwang/img/menu-icon.png
Qt5BianchengRumenjiaochengCYuyanZhongwenwang/img/save.png
Qt5BianchengRumenjiaochengCYuyanZhongwenwang/img/saved.png
Qt5BianchengRumenjiaochengCYuyanZhongwenwang/img/settings-s.png
Qt5BianchengRumenjiaochengCYuyanZhongwenwang/img/settings.png
Qt5BianchengRumenjiaochengCYuyanZhongwenwang/img/star.png
Qt5BianchengRumenjiaochengCYuyanZhongwenwang/js/__init__.py
Qt5BianchengRumenjiaochengCYuyanZhongwenwang/js/epub.js
Qt5BianchengRumenjiaochengCYuyanZhongwenwang/js/epub.min.js
qt5_biancheng_rumenjiaocheng_c_yuyan_zhongwenwang-2024.3.5.0.dist-info/METADATA
qt5_biancheng_rumenjiaocheng_c_yuyan_zhongwenwang-2024.3.5.0.dist-info/WHEEL
qt5_biancheng_rumenjiaocheng_c_yuyan_zhongwenwang-2024.3.5.0.dist-info/entry_points.txt
qt5_biancheng_rumenjiaocheng_c_yuyan_zhongwenwang-2024.3.5.0.dist-info/top_level.txt
qt5_biancheng_rumenjiaocheng_c_yuyan_zhongwenwang-2024.3.5.0.dist-info/RECORD
